{"counter":{"8/4/2018.12":{"simpletext":13,"simpleimage":21,"simplevideo":25,"exponent":19,"template":3},"8/4/2018.13":{"simpletext":15,"simpleimage":20,"simplevideo":22,"exponent":12,"template":8},"8/4/2018.15":{"simpletext":23,"simpleimage":11,"simplevideo":13,"exponent":4,"template":7},"8/4/2018.16":{"simpletext":33,"simpleimage":33,"simplevideo":33,"exponent":5,"template":2},"8/4/2018.17":{"simpleimage":58,"simplevideo":58,"simpletext":57,"exponent":3},"8/4/2018.18":{"simpleimage":34,"simplevideo":34,"simpletext":33,"template":4,"exponent":3},"8/4/2018.19":{"simpleimage":54,"simplevideo":54,"simpletext":53,"exponent":5,"template":1},"8/4/2018.21":{"simpleimage":8,"simplevideo":8,"simpletext":7,"exponent":1,"template":1},"8/4/2018.22":{"simpleimage":56,"simplevideo":55,"simpletext":55,"template":1,"exponent":1},"8/5/2018.10":{"simpleimage":13,"simplevideo":13,"exponent":2,"simpletext":12},"8/5/2018.11":{"simpleimage":37,"simplevideo":37,"simpletext":36,"template":4,"template/5":1},"8/5/2018.12":{"simpleimage":43,"simplevideo":43,"simpletext":45,"template":11,"lib/bootstrap-colorpicker.min.js.map":7,"lib/bootstrap-colorpicker.min.css.map":7,"template/5":6,"template/4":1,"exponent":6},"8/5/2018.13":{"template":22,"simpletext":35,"simpleimage":35,"simplevideo":35,"lib/bootstrap-colorpicker.min.css.map":22,"template/5":18,"lib/bootstrap-colorpicker.min.js.map":21,"exponent":7},"8/5/2018.19":{"lib/bootstrap-colorpicker.min.css.map":12,"template":17,"simpletext":31,"simpleimage":29,"simplevideo":29,"lib/bootstrap-colorpicker.min.js.map":11,"template/5":8,"exponent":13},"8/5/2018.20":{"simpleimage":31,"simplevideo":31,"exponent":14,"simpletext":33,"template":5,"exponent/5":10,"template/3":2,"exponent?uuid=testcollection":1,"exponent/13":1},"8/6/2018.20":{"simpleimage":4,"simplevideo":4,"simpletext":12},"8/7/2018.7":{"simpleimage":13,"simplevideo":14,"simpletext":14,"exponent":4,"template":3,"template/6":1},"8/8/2018.6":{"simpletext":1,"simplevideo":1,"simpleimage":1},"2018-10-5.19":{"simpleimage":36,"simplevideo":36,"html":1,"simpletext":40,"exponent":4,"exponent/10":1,"exponent/11":1,"exponent/13":1,"template":7,"template/4":3,"template/6":3,"lib/bootstrap-colorpicker.min.js.map":3,"lib/bootstrap-colorpicker.min.css.map":3,"template/5":2},"2018-10-5.20":{"simpleimage":37,"simplevideo":37,"simpletext":40,"exponent":1,"simpletext/11":3,"simpletext/12":11,"simpletext/13":1},"2018-10-5.21":{"simpleimage":1,"simplevideo":1},"2018-10-6.9":{"simpleimage":4,"simplevideo":4,"simpletext":3,"simpletext/12":2},"2018-10-6.10":{"simpletext":33,"simpleimage":30,"simplevideo":30,"simpletext/13":1,"simpletext/12":2,"simpletext?id=12":16,"template":1,"exponent":1,"exponent/5":1},"2018-10-6.11":{"simpleimage":29,"simplevideo":29,"simpletext":36,"simpletext?id=12":12,"simpletext/12":15,"exponent":1,"simpletext?id=17":4,"simpletext/17":29},"2018-10-6.12":{"simpletext":47,"simplevideo":42,"simpleimage":42,"simpletext?id=17":22,"simpletext/17":26,"simpletext?id=12":30,"simpletext/12":30,"public/favicon.png":3,"exponent":1},"2018-10-7.12":{"simpleimage":9,"simplevideo":9,"simpletext":9,"exponent":1},"2018-10-7.13":{"simpletext":46,"simpleimage":36,"simplevideo":36,"simpletext/16":1,"simpletext/14":1,"simpletext/15":1,"exponent":5,"exponent/9":1,"exponent/10":1,"exponent/11":1,"exponent/12":2,"exponent/5":1,"simpletext?id=17":3,"simpletext?id=12":16,"api/login":1,"simplecms/api/login":1},"2018-10-7.14":{"simpletext":19,"simpleimage":18,"simplevideo":18,"simpletext?id=12":16,"simpletext/17":2},"2018-10-7.15":{"simpleimage":17,"simplevideo":17,"simpletext":19,"simpletext?id=12":3,"simpletext?id=17":3,"simpletext/12":2,"exponent":2,"exponents?uuid=redCoral":2,"simplecms/exponents?uuid=redCoral":1,"exponent?uuid=redCoral":1}}}